[{"id":"look1","category":"Vêtements","name":"Combinaison Bleu et Blanc","description":"Combinaison femme à rayures bleues et blanches, style dos nu avec boucle décorative, taille cintrée et jambes larges.","price":"79 TND","source":"SHEIN","size":"38(M)","badge":"En stock","images":["images/comb1.jpg","images/comb2.jpg","images/comb3.jpg"]},
{"id":"look2","category":"Vêtements","name":"Robe Kaki","description":"Robe ajustée avec taille cintrée, col ras-du-cou et poches, couleur kaki.","price":"79 TND","source":"SHEIN","size":"38(M)","badge":"En stock","images":["images/robekaki3.jpg","images/robekaki1.jpg","images/robekaki2.jpg"]},
{"id":"look3","category":"Vêtements","name":"Blouse Militaire verte","description":"Blouse décontractée à manches longues avec boutons devant et épaules tombantes, couleur unie.","price":"60 TND","source":"SHEIN","size":"40/42(L)","badge":"En stock","images":["images/blouse3.jpg","images/blouse2.jpg","images/blouse1.jpg"]},
{"id":"look4","category":"Vêtements","name":"Chemise Bleu azur","description":"Chemise élégante à manches longues pour le bureau avec boutons devant et bordure contrastée.","price":"70 TND","source":"SHEIN","size":"38(M)","badge":"En stock","images":["images/chemisebleu3.jpg","images/chemisebleu2.jpg","images/chemisebleu1.jpg"]},
{"id":"look5","category":"Vêtements","name":"Blazer Nude","description":"Blazer régulier décontracté à rayures et patchwork avec un bouton pour femmes, printemps.","price":"97 TND","source":"SHEIN","size":"38(M)","badge":"En stock","images":["images/blazernude3.jpg","images/blazernude2.jpg","images/blazernude1.jpg"]},
{"id":"look6","category":"Vêtements","name":"Blazer noir","description":"Blazer régulier décontracté à rayures et patchwork avec un bouton pour femmes, printemps.","price":"97 TND","source":"SHEIN","size":"40/42(L)","badge":"En stock","images":["images/blazernoir3.jpg","images/blazernoir2.jpg","images/blazernoir1.jpg"]},
{"id":"look7","category":"Vêtements","name":"Robe de chambre Rose bonbon","description":"Robe de chambre élégante à taille nouée de couleur unie pour femmes, automne/hiver. Nuisette courte en satin de soie douce et sexy, convient pour les mariées, demoiselles d'honneur, tenue d'intérieur. Robe courte de saison des mariages, motif lettre, robe et pyjama.","price":"32 TND","source":"SHEIN","size":"M","badge":"En stock","images":["images/rbchambrerose3.jpg","images/rbchambrerose2.jpg","images/rbchambrerose1.jpg"]},
{"id":"look8","category":"Vêtements","name":"Robe de chambre Kaki","description":"Robe de chambre élégante à taille nouée de couleur unie pour femmes, automne/hiver. Nuisette courte en satin de soie douce et sexy, convient pour les mariées, demoiselles d'honneur, vêtements d'intérieur. Robe courte de saison des mariages, motif de lettres, robe et pyjama.","price":"32 TND","source":"SHEIN","size":"L","badge":"En stock","images":["images/rbchambrekaki3.jpg","images/rbchambrekaki2.jpg","images/rbchambrekaki1.jpg"]},
{"id":"look9","category":"Vêtements","name":"Robe Noir","description":"Robe Camisole, Ours Endormi Noir.","price":"38 TND","source":"SHEIN","size":"M","badge":"En stock","images":["images/robenoir1.avif","images/robenoir2.avif"]},

{"id":"ling1","category":"Lingerie","name":"Ensemble lingerie bleu indigo","description":"Ensemble de lingerie sexy et confortable de style européen et américain pour dames, bleu indigo","price":"26 TND","source":"SHEIN","size":"L","badge":"En stock","images":["images/lingbleu3.jpg","images/lingbleu2.jpg","images/lingbleu1.jpg"]},
{"id":"ling2","category":"Lingerie","name":"Nuisette Nude","description":"Nuisette en satin à imprimé floral sans manches pour femmes, vêtement de détente de luxe","price":"26 TND","source":"SHEIN","size":"38(M)","badge":"En stock","images":["images/nuisettenude3.jpg","images/nuisettenude2.jpg","images/nuisettenude1.jpg"]},
{"id":"ling3","category":"Lingerie","name":"Ensemble de pyjama Prune","description":"Ensemble de pyjama femme composé d'un débardeur et d'un short de couleur unie","price":"28 TND","source":"SHEIN","size":"38(M)","badge":"En stock","images":["images/prune1.jpg","images/prune2.jpg","images/prune3.jpg"]},
{"id":"ling4","category":"Lingerie","name":"Combinaison mauve","description":"Combinaison de pyjama romantique d'été pour femmes avec imprimé fraise, cœur et marguerite","price":"26 TND","source":"SHEIN","size":"38(M)","badge":"En stock","images":["images/mauve1.jpg","images/mauve2.jpg","images/mauve3.jpg"]},
{"id":"ling5","category":"Lingerie","name":"Nuisette fleurie","description":"Nuisette fleurie imprimée décontractée pour femmes","price":"26 TND","source":"SHEIN","size":"38(M)","badge":"En stock","images":["images/nuisettefleur1.jpg","images/nuisettefleur2.jpg","images/nuisettefleur3.jpg"]},
{"id":"ling6","category":"Lingerie","name":"Combinaison Acajou","description":"Combinaison short en couleur unie avec col carré pour femme, Acajou.","price":"34 TND","source":"SHEIN","size":"38(M)","badge":"En stock","images":["images/acajou1.jpg","images/acajou2.jpg","images/acajou3.jpg"]},
{"id":"ling7","category":"Lingerie","name":"Lingerie Bleu marine","description":"Soutien-gorge à bordure de dentelle florale et shorts en satin, lingerie.","price":"33 TND","source":"SHEIN","size":"M","badge":"En stock","images":["images/lingmarine1.jpg","images/lingmarine2.jpg","images/lingmarine3.jpg"]},
{"id":"ling8","category":"Lingerie","name":"Lingerie Rose fuchsia","description":"Soutien-gorge en dentelle florale avec short en satin, lingerie.","price":"33 TND","source":"SHEIN","size":"M","badge":"En stock","images":["images/lingrose1.jpg","images/lingrose2.jpg","images/lingrose3.jpg"]},
{"id":"ling9","category":"Lingerie","name":"Robe de nuit Rouge foncé","description":"Robe de nuit chemise à bretelles avec imprimé cœur simple.","price":"29 TND","source":"SHEIN","size":"40/42(L)","badge":"En stock","images":["images/lingrougefonc1.jpg","images/lingrougefonc2.jpg","images/lingrougefonc3.jpg"]},
{"id":"ling10","category":"Lingerie","name":"Nuisette Bleu marine","description":"Nuisette de pyjama avec imprimé nœud et ornement de laitue.","price":"27 TND","source":"SHEIN","size":"38(M)","badge":"En stock","images":["images/lingbleumarine1.jpg","images/lingbleumarine2.jpg","images/lingbleumarine3.jpg"]},
{"id":"ling11","category":"Lingerie","name":"Nuisette Noir","description":"Nuisette de pyjama avec imprimé papillon et garniture de laitue","price":"23 TND","source":"SHEIN","size":"38(M)","badge":"En stock","images":["images/lingnoirr1.jpg","images/lingnoirr2.jpg","images/lingnoirr3.jpg"]},
{"id":"ling12","category":"Lingerie","name":"2 pièces à imprimé léopard","description":"2 pièces Ensemble de string sans couture à imprimé léopard et dentelle contrastée, lingerie","price":"26 TND","source":"SHEIN","size":"M","badge":"En stock","images":["images/leo1.jpg","images/leo2.jpg","images/leo3.jpg"]},
{"id":"ling13","category":"Lingerie","name":"Nuisette à imprimé cœurs","description":"Nuisette femme à bretelles fines avec imprimé cœurs tout-sur-tout, vêtement d'intérieur décontracté","price":"26 TND","source":"SHEIN","size":"40/42(L)","badge":"En stock","images":["images/nuiscoeur1.jpg","images/nuiscoeur2.jpg","images/nuiscoeur3.jpg"]},
{"id":"ling14","category":"Lingerie","name":"Ensemble de pyjama","description":"Ensemble de pyjama avec camisole et short, avec empiècement coloré, volants et imprimé d'étoile et de lune sur l'ours","price":"27 TND","source":"SHEIN","size":"40/42(L)","badge":"En stock","images":["images/ours1.jpg","images/ours2.jpg","images/ours3.jpg"]},
{"id":"ling15","category":"Lingerie","name":"Robe de nuit Rose bonbon","description":"Robe de nuit à bretelles spaghetti imprimée florale","price":"30 TND","source":"SHEIN","size":"38(M)","badge":"Reservé","images":["images/rsebonbon1.jpg","images/rsebonbon2.jpg","images/rsebonbon3.jpg"]},
{"id":"ling16","category":"Lingerie","name":"2 pièces Blanc","description":"Set de soutien-gorge et culotte en dentelle de couleur unie pour femme, sous-vêtements de confort et armature. Lingerie de mariée","price":"28 TND","source":"SHEIN","size":"M","badge":"En stock","images":["images/2pieceblanc.webp"]},
{"id":"ling17","category":"Lingerie","name":"Combinaison-short Rose","description":"Combinaison-short sans manches imprimée de cœurs de fraises et de marguerites romantiques pour femmes, idéale pour l'été","price":"26 TND","source":"SHEIN","size":"40/42(L)","badge":"En stock","images":["images/combrose1.jpg","images/combrose2.jpg","images/combrose3.jpg"]},
{"id":"ling18","category":"Lingerie","name":"2 pièces Rouge foncé","description":"2 pièces Ensemble de lingerie pour femmes avec broderie florale sexy en maille et nœud décoratif","price":"56 TND","source":"SHEIN","size":"L","badge":"En stock","images":["images/2piecerougefonce1.jpg","images/2piecerougefonce2.jpg","images/2piecerougefonce3.jpg"]},
{"id":"ling19","category":"Lingerie","name":"2 pièces Rose bonbon","description":"2 pièces Ensemble de lingerie soutien-gorge et culotte sexy pour femmes avec dentelle brodée","price":"40 TND","source":"SHEIN","size":"L","badge":"En stock","images":["images/2piecerose1.jpg","images/2piecerose2.jpg","images/2piecerose1.jpg"]},
{"id":"ling20","category":"Lingerie","name":"Set Lingerie","description":"Soutien-gorge bandeau en dentelle florale avec short en satin, lingerie","price":"31 TND","source":"SHEIN","size":"L","badge":"En stock","images":["images/setling1.jpg","images/setling2.jpg","images/setling3.jpg"]},
{"id":"ling21","category":"Lingerie","name":"Nuisette Rose bonbon","description":"Nuisette fendue avec garniture en dentelle rose pour femmes","price":"37 TND","source":"SHEIN","size":"40/42(L)","badge":"En stock","images":["images/nuisrose1.jpg","images/nuisrose2.jpg","images/nuisrose3.jpg"]},
{"id":"ling22","category":"Lingerie","name":"Nuisette Rouge foncé","description":"Nuisette de pyjama à fente ourlet avec dentelle contrastante","price":"40 TND","source":"SHEIN","size":"40/42(L)","badge":"En stock","images":["images/nuisroug1.jpg","images/nuisroug2.jpg","images/nuisroug3.jpg"]},

{"id":"bag1","category":"Sacs et accessoires","name":"Sac bandoulière Blanc","description":"Sac Bandoulière Femme en PU Matelassé Ondulé, Tête de Fermeture Éclair en Métal.","price":"45 TND","source":"SHEIN","badge":"En stock","images":["images/sacblanc.avif"]},
{"id":"bag2","category":"Sacs et accessoires","name":"Sac bandoulière Marron clair","description":"Sac à bandoulière tissé style bohème, bandoulière réglable.","price":"36 TND","source":"SHEIN","badge":"Reservé","images":["images/sacmarron.avif"]},
{"id":"bag3","category":"Sacs et accessoires","name":"Sac à main Noir","description":"Sac à Main Portefeuille Multifonctionnel pour Femmes avec Fermeture Éclair Longue.","price":"28 TND","source":"SHEIN","badge":"En stock","images":["images/sacnoir.avif"]},
{"id":"bag4","category":"Sacs et accessoires","name":"Ceinture vintage","description":"Ceinture Femme Vintage à Maillons Circulaires.","price":"19 TND","source":"SHEIN","badge":"En stock","images":["images/centvintage1.avif"]},
{"id":"bag5","category":"Sacs et accessoires","name":"Ceinture extensible Kaki","description":"Accessoires de robe Ceinture extensible.","price":"25 TND","source":"SHEIN","badge":"En stock","images":["images/centext1.avif","images/centext3.avif"]},
{"id":"bag6","category":"Sacs et accessoires","name":"Ceinture extensible Noir Doré","description":"Accessoires de robe Ceinture extensible.","price":"18 TND","source":"SHEIN","badge":"En stock","images":["images/centext2.avif","images/centext3.avif"]},
{"id":"bag7","category":"Sacs et accessoires","name":"3 pièces Ceintures 3 couleurs","description":"3 pièces Ceinture Fine à Boucle Cœur Doré pour Femme, Ceintures Simples et Tendances pour Jeans et Robes.","price":"35 TND","source":"SHEIN","badge":"En stock","images":["images/3piececent.avif"]},
{"id":"bag8","category":"Sacs et accessoires","name":"4 pièces Ceintures 4 couleurs","description":"4 pièces Ceintures à boucle à aiguille de couleur unie, style décontracté et professionnel, polyvalentes pour jupes et pantalons.","price":"40 TND","source":"SHEIN","badge":"Reservé","images":["images/4piececent.avif"]},
{"id":"bag9","category":"Sacs et accessoires","name":"2 pièces Bonnet de nuit Rose+Noir","description":"2 pièces Bonnet en soie pour dormir, bonnets à cheveux en satin, bonnet de nuit en soie à bande élastique douce.","price":"15 TND","source":"SHEIN","badge":"En stock","images":["images/bonnet1.jpg","images/bonnet2.jpg","images/bonnet3.jpg"]},
{"id":"bag10","category":"Sacs et accessoires","name":"Bonnet de sommeil Doré","description":"Bonnet de sommeil Doré","price":"10 TND","source":"SHEIN","badge":"En stock","images":["images/bnndore1.jpg","images/bnndore2.jpg","images/bnndore3.jpg"]},

{"id":"bag11","category":"Sacs et accessoires","name":"5 paires de chaussettes 5 couleurs","description":"5 paire de chaussettes bateau à bouche profonde...","price":"17 TND","source":"SHEIN","badge":"En stock","images":["images/chaussete1.jpg","images/chaussete2.jpg","images/chaussete3.jpg"]},
{"id":"bag12","category":"Sacs et accessoires","name":"5 paires chaussettes 2 noirs, 2 peaux, 1 blanc","description":"5 paires/set Chaussettes invisibles en dentelle...","price":"17 TND","source":"SHEIN","badge":"En stock","images":["images/chauss1.jpg","images/chauss2.jpg","images/chauss3.jpg"]},
{"id":"bag13","category":"Sacs et accessoires","name":"1 Paire de collants","description":"1 paire de collants femme à motif cœur...","price":"12 TND","source":"SHEIN","size":"L","badge":"En stock","images":["images/collant1.jpg","images/collant2.jpg"]},
{"id":"bag14","category":"Sacs et accessoires","name":"5 pièces Bracelet","description":"5 pièces Bracelet ouvert géométrique...","price":"18 TND","source":"SHEIN","size":"Diamètre: 6-7, Longueur: 17-22.5","badge":"En stock","images":["images/bracelet2.jpg","images/bracelet1.jpg"]},
{"id":"bag15","category":"Sacs et accessoires","name":"11 paires Boucles d'oreilles","description":"11 paires/set Boucles d'oreilles...","price":"32 TND","source":"SHEIN","badge":"En stock","images":["images/11paires1.jpg","images/11paires2.jpg"]},
{"id":"bag16","category":"Sacs et accessoires","name":"6 paires Boucles d'oreilles","description":"Ensemble de Boucles d'Oreilles Style Bohème...","price":"16 TND","source":"SHEIN","badge":"En stock","images":["images/6paires1.avif"]},
{"id":"bag17","category":"Sacs et accessoires","name":"6 paires Boucles d'oreilles","description":"Ensemble de Boucles d'Oreilles Style Bohème...","price":"16 TND","source":"SHEIN","badge":"En stock","images":["images/6paires2.avif"]},
{"id":"bag18","category":"Sacs et accessoires","name":"6 paires Boucles d'oreilles","description":"Ensemble de Boucles d'Oreilles Style Bohème...","price":"16 TND","source":"SHEIN","badge":"En stock","images":["images/6paires3.avif"]},
{"id":"bag19","category":"Sacs et accessoires","name":"6 paires Boucles d'oreilles","description":"Ensemble de Boucles d'Oreilles Style Bohème...","price":"16 TND","source":"SHEIN","badge":"En stock","images":["images/6paires4.avif"]},
{"id":"bag20","category":"Sacs et accessoires","name":"Set 10 Boutons","description":"10 Boutons multifonctionnels élégants...","price":"15 TND","source":"SHEIN","badge":"En stock","images":["images/boutons.avif"]},
{"id":"bag21","category":"Sacs et accessoires","name":"Ensemble de 21 bagues","description":"Ensemble de 21 bagues pour femmes...","price":"35 TND","source":"SHEIN","badge":"En stock","images":["images/bagues1.avif","images/bagues2.avif","images/bagues3.avif"]},
{"id":"bag22","category":"Sacs et accessoires","name":"Ensemble de 12 bracelets","description":"Ensemble de 12 bracelets élégants...","price":"28 TND","source":"SHEIN","badge":"Reservé","images":["images/brac1.avif","images/brac1.avif","images/brac1.avif"]},

{"id":"cosmetic1","category":"Produits Beauté","name":"5 pièces Ensemble de pinceaux","description":"5 pièces Ensemble de pinceaux...","price":"10 TND","source":"SHEIN","badge":"En stock","images":["images/pinc1.jpg","images/pinc2.jpg"]},
{"id":"cosmetic2","category":"Produits Beauté","name":"Set de kit de pinceaux","description":"Set de kit de pinceaux...","price":"29 TND","source":"SHEIN","badge":"En stock","images":["images/setpinc1.jpg","images/setpinc2.jpg","images/setpinc3.jpg"]},
{"id":"cosmetic3","category":"Produits Beauté","name":"13 pièces Set de pinceaux","description":"13 pièces Set de pinceaux...","price":"39 TND","source":"SHEIN","badge":"En stock","images":["images/13piece1.jpg","images/13piece2.jpg","images/13piece3.jpg"]},
{"id":"cosmetic4","category":"Produits Beauté","name":"Boîte à bijoux Rose","description":"Boîte à bijoux de voyage portable...","price":"32 TND","source":"SHEIN","badge":"En stock","images":["images/btebijou1.jpg","images/btebijou2.jpg","images/btebijou3.jpg"]}
]
